nendo/__init__.py
nendo/config.py
nendo/library/__init__.py
nendo/library/duckdb_library.py
nendo/library/extension.py
nendo/library/model.py
nendo/library/sqlalchemy_library.py
nendo/main.py
nendo/schema/__init__.py
nendo/schema/core.py
nendo/schema/exception.py
nendo/schema/plugin.py
nendo/utils.py
nendo-0.2.5.dist-info/LICENSE
nendo-0.2.5.dist-info/METADATA
nendo-0.2.5.dist-info/WHEEL
nendo-0.2.5.dist-info/RECORD
