Metadata-Version: 2.1
Name: nendo
Version: 0.2.5
Summary: The Nendo AI Audio Tool Suite
Home-page: https://okio.ai
License: MIT
Keywords: AI,Machine Learning,Audio,Generative,Music,Audio Production,Audio Generation,Audio Analysis
Author: Okio Team
Author-email: team@okio.ai
Requires-Python: >=3.8,<3.11
Classifier: Development Status :: 5 - Production/Stable
Classifier: Intended Audience :: Developers
Classifier: License :: OSI Approved :: MIT License
Classifier: Operating System :: OS Independent
Classifier: Programming Language :: Python :: 3
Classifier: Programming Language :: Python :: 3.8
Classifier: Programming Language :: Python :: 3.9
Classifier: Programming Language :: Python :: 3.10
Classifier: Topic :: Multimedia :: Sound/Audio
Provides-Extra: dev
Provides-Extra: doc
Requires-Dist: GitPython (>=3.1.40,<4.0.0) ; extra == "doc"
Requires-Dist: alembic (>=1.12.0,<2.0.0) ; extra == "dev"
Requires-Dist: black (>=23.1.0,<24.0.0) ; extra == "dev"
Requires-Dist: coverage (>=7.3.2,<8.0.0) ; extra == "dev"
Requires-Dist: duckdb-engine (>=0.9.0,<0.10.0)
Requires-Dist: freezegun (>=1.2.2,<2.0.0) ; extra == "dev"
Requires-Dist: git_changelog (>=2.3.2,<3.0.0) ; extra == "dev"
Requires-Dist: librosa (>=0.10.0,<0.11.0)
Requires-Dist: markdown-callouts (>=0.3.0,<0.4.0) ; extra == "doc"
Requires-Dist: markdown-exec (>=1.7.0,<2.0.0) ; extra == "doc"
Requires-Dist: materialx (>=1.38.8,<2.0.0) ; extra == "doc"
Requires-Dist: mkdocs (>=1.5.3,<2.0.0) ; extra == "doc"
Requires-Dist: mkdocs-autorefs (>=0.5.0,<0.6.0) ; extra == "doc"
Requires-Dist: mkdocs-coverage (>=1.0.0,<2.0.0) ; extra == "doc"
Requires-Dist: mkdocs-gen-files (>=0.5.0,<0.6.0) ; extra == "doc"
Requires-Dist: mkdocs-git-committers-plugin-2 (>=2.2.0,<3.0.0) ; extra == "doc"
Requires-Dist: mkdocs-literate-nav (>=0.6.1,<0.7.0) ; extra == "doc"
Requires-Dist: mkdocs-material (>=9.4.7,<10.0.0) ; extra == "doc"
Requires-Dist: mkdocs-minify-plugin (>=0.7.1,<0.8.0) ; extra == "doc"
Requires-Dist: mkdocs-monorepo-plugin (>=1.1.0,<2.0.0) ; extra == "doc"
Requires-Dist: mkdocs-pymdownx-material-extras (>=2.5.5,<3.0.0) ; extra == "doc"
Requires-Dist: mkdocs-redirects (>=1.2.1,<2.0.0) ; extra == "doc"
Requires-Dist: mkdocs-swagger-ui-tag (>=0.6.8,<0.7.0)
Requires-Dist: mkdocstrings-python (>=1.7.3,<2.0.0) ; extra == "doc"
Requires-Dist: numpy (>=1.20,<2.0)
Requires-Dist: pydantic (>=2.0.0,<2.5.0)
Requires-Dist: pydantic-settings (>=2.1.0,<3.0.0)
Requires-Dist: pytest (>=7.3.0,<8.0.0) ; extra == "dev"
Requires-Dist: pytz (==2023.3.post1)
Requires-Dist: rich (>=12.5.1,<13.0.0)
Requires-Dist: ruff (>=0.2.2,<0.3.0) ; extra == "dev"
Requires-Dist: setuptools (>=67.6.1,<68.0.0) ; extra == "dev"
Requires-Dist: sounddevice (>=0.4.6,<0.5.0)
Requires-Dist: soundfile (>=0.12,<0.13)
Requires-Dist: sqlalchemy (>=2.0.25,<3.0.0)
Requires-Dist: sqlalchemy-json (>=0.7.0,<0.8.0)
Requires-Dist: tinytag (>=1.8,<2.0)
Requires-Dist: toml (>=0.10.2,<0.11.0) ; extra == "dev"
Project-URL: Repository, https://github.com/okio-ai/nendo
